airflow_providers_lokalise-1.2.2.dist-info/licenses/LICENSE
lokalise_provider/__init__.py
lokalise_provider/hooks/__init__.py
lokalise_provider/hooks/lokalise.py
lokalise_provider/operators/__init__.py
lokalise_provider/operators/lokalise.py
airflow_providers_lokalise-1.2.2.dist-info/METADATA
airflow_providers_lokalise-1.2.2.dist-info/WHEEL
airflow_providers_lokalise-1.2.2.dist-info/entry_points.txt
airflow_providers_lokalise-1.2.2.dist-info/top_level.txt
airflow_providers_lokalise-1.2.2.dist-info/RECORD
