Metadata-Version: 2.4
Name: airflow-providers-lokalise
Version: 1.2.2
Summary: Lokalise hook and operator for Airflow based on the Lokalise Python SDK
Author-email: Jonathan Perron <contact@jonathanperron.fr>
License: BSD 3
Project-URL: Source, https://github.com/jonperron/airflow-provider-lokalise
Classifier: Framework :: Apache Airflow
Classifier: Framework :: Apache Airflow :: Provider
Requires-Python: >=3.10
License-File: LICENSE
Requires-Dist: apache-airflow>=2.7
Requires-Dist: apache-airflow-providers-postgres<7,>=6.0.0
Requires-Dist: python-lokalise-api<4,>=3.0.0
Dynamic: license-file
